helium/__init__.py
helium/__main__.py
helium/cli.py
helium/service.py
helium/version.py
helium/commands/__init__.py
helium/commands/cloud-script.py
helium/commands/element.py
helium/commands/label.py
helium/commands/organization.py
helium/commands/sensor-script.py
helium/commands/sensor.py
helium/commands/timeseries.py
helium/commands/user.py
helium/commands/util.py
helium/commands/writer.py
helium_commander-0.9.3.dist-info/DESCRIPTION.rst
helium_commander-0.9.3.dist-info/METADATA
helium_commander-0.9.3.dist-info/RECORD
helium_commander-0.9.3.dist-info/WHEEL
helium_commander-0.9.3.dist-info/entry_points.txt
helium_commander-0.9.3.dist-info/metadata.json
helium_commander-0.9.3.dist-info/top_level.txt
