Metadata-Version: 2.0
Name: helium-commander
Version: 0.9.3
Summary: A CLI and service wrapper for the Helium API
Home-page: http://github.com/helium/helium-commander/
Author: Marc Nijdam
Author-email: marc@helium.com
License: BSD
Platform: all
Classifier: Development Status :: 4 - Beta
Classifier: Environment :: Web Environment
Classifier: Intended Audience :: Developers
Classifier: License :: OSI Approved :: BSD License
Classifier: Operating System :: OS Independent
Classifier: Programming Language :: Python
Classifier: Topic :: Utilities
Classifier: Topic :: Software Development :: Libraries :: Python Modules
Requires-Dist: click (>=6.6)
Requires-Dist: dpath (>=1.4)
Requires-Dist: future (>=0.15)
Requires-Dist: futures (>=3.0)
Requires-Dist: requests (>=2.9)
Requires-Dist: terminaltables (>=2.1.0)
Requires-Dist: unicodecsv (>=0.14.1)
